elfhub/__init__.py
elfhub/base.py
elfhub-0.0.1.dist-info/METADATA
elfhub-0.0.1.dist-info/WHEEL
elfhub-0.0.1.dist-info/top_level.txt
elfhub-0.0.1.dist-info/RECORD
