Metadata-Version: 2.4
Name: elfhub
Version: 0.0.1
Summary: Package Setup
Author-email: Eshan Chawla <admin@elfhub.ai>
Classifier: Programming Language :: Python :: 3
Classifier: License :: OSI Approved :: MIT License
Classifier: Operating System :: OS Independent
Requires-Python: >=3.8
